{
  "AL": {
    "electoralVotes": 9,
    "name": "Alabama"
  },

  "AK": {
    "electoralVotes": 3,
    "name": "Alaska"
  },

  "AZ": {
    "electoralVotes": 11,
    "name": "Arizona"
  },

  "AR": {
    "electoralVotes": 6,
    "name": "Arkansas"
  },

  "CA": {
    "electoralVotes": 55,
    "name": "California"
  },

  "CO": {
    "electoralVotes": 9,
    "name": "Colorado"
  },

  "CT": {
    "electoralVotes": 7,
    "name": "Connecticut"
  },

  "DE": {
    "electoralVotes": 3,
    "name": "Delaware"
  },

  "DC": {
    "electoralVotes": 3,
    "name": "District of Columbia"
  },

  "FL": {
    "electoralVotes": 29,
    "name": "Florida"
  },

  "GA": {
    "electoralVotes": 16,
    "name": "Georgia"
  },

  "HI": {
    "electoralVotes": 4,
    "name": "Hawaii"
  },

  "ID": {
    "electoralVotes": 4,
    "name": "Idaho"
  },

  "IL": {
    "electoralVotes": 20,
    "name": "Illinois"
  },

  "IN": {
    "electoralVotes": 11,
    "name": "Indiana"
  },

  "IA": {
    "electoralVotes": 6,
    "name": "Iowa"
  },

  "KS": {
    "electoralVotes": 6,
    "name": "Kansas"
  },

  "KY": {
    "electoralVotes": 8,
    "name": "Kentucky"
  },

  "LA": {
    "electoralVotes": 8,
    "name": "Louisiana"
  },

  "ME": {
    "electoralVotes": 4,
    "name": "Maine"
  },

  "MD": {
    "electoralVotes": 10,
    "name": "Maryland"
  },

  "MA": {
    "electoralVotes": 11,
    "name": "Massachusetts"
  },

  "MI": {
    "electoralVotes": 16,
    "name": "Michigan"
  },

  "MN": {
    "electoralVotes": 10,
    "name": "Minnesota"
  },

  "MS": {
    "electoralVotes": 6,
    "name": "Mississippi"
  },

  "MO": {
    "electoralVotes": 10,
    "name": "Missouri"
  },

  "MT": {
    "electoralVotes": 3,
    "name": "Montana"
  },

  "NE": {
    "electoralVotes": 5,
    "name": "Nebraska"
  },

  "NV": {
    "electoralVotes": 6,
    "name": "Nevada"
  },

  "NH": {
    "electoralVotes": 4,
    "name": "New Hampshire"
  },

  "NJ": {
    "electoralVotes": 14,
    "name": "New Jersey"
  },

  "NM": {
    "electoralVotes": 5,
    "name": "New Mexico"
  },

  "NY": {
    "electoralVotes": 29,
    "name": "New York"
  },

  "NC": {
    "electoralVotes": 15,
    "name": "North Carolina"
  },

  "ND": {
    "electoralVotes": 3,
    "name": "North Dakota"
  },

  "OH": {
    "electoralVotes": 18,
    "name": "Ohio"
  },

  "OK": {
    "electoralVotes": 7,
    "name": "Oklahoma"
  },

  "OR": {
    "electoralVotes": 7,
    "name": "Oregon"
  },

  "PA": {
    "electoralVotes": 20,
    "name": "Pennsylvania"
  },

  "RI": {
    "electoralVotes": 4,
    "name": "Rhode Island"
  },

  "SC": {
    "electoralVotes": 9,
    "name": "South Carolina"
  },

  "SD": {
    "electoralVotes": 3,
    "name": "South Dakota"
  },

  "TN": {
    "electoralVotes": 11,
    "name": "Tennessee"
  },

  "TX": {
    "electoralVotes": 38,
    "name": "Texas"
  },

  "UT": {
    "electoralVotes": 6,
    "name": "Utah"
  },

  "VT": {
    "electoralVotes": 3,
    "name": "Vermont"
  },

  "VA": {
    "electoralVotes": 13,
    "name": "Virginia"
  },

  "WA": {
    "electoralVotes": 12,
    "name": "Washington"
  },

  "WV": {
    "electoralVotes": 5,
    "name": "West Virginia"
  },

  "WI": {
    "electoralVotes": 10,
    "name": "Wisconsin"
  },

  "WY": {
    "electoralVotes": 3,
    "name": "Wyoming"
  }
}